bot_common/__init__.py
bot_common/lib_conf.py
bot_common/apis/__init__.py
bot_common/apis/api_request.py
bot_common/companies/__init__.py
bot_common/companies/company.py
bot_common/companies/company_model.py
bot_common/companies/company_setup.py
bot_common/exceptions/__init__.py
bot_common/exceptions/exception.py
bot_common/exceptions/exception_model.py
bot_common/logs/__init__.py
bot_common/logs/log.py
bot_common/logs/log_model.py
bot_common/messages/__init__.py
bot_common/messages/message.py
bot_common/messages/message_model.py
bot_common/messages/timeout.py
bot_common/messages/timeout_model.py
bot_common/send_message/__init__.py
bot_common/send_message/mail.py
bot_common/send_message/mail_model.py
bot_common/sessions/__init__.py
bot_common/sessions/session.py
bot_common/sessions/session_model.py
bot_common/utils/__init__.py
bot_common/utils/db_utils.py
bot_common/utils/logging_conf.py
bot_common/utils/utils.py
bot_common-0.2.1.dist-info/licenses/LICENSE
bot_common-0.2.1.dist-info/METADATA
bot_common-0.2.1.dist-info/WHEEL
bot_common-0.2.1.dist-info/top_level.txt
bot_common-0.2.1.dist-info/RECORD
