Metadata-Version: 2.4
Name: bot_common
Version: 0.2.1
Summary: Common libraries AISAC Bot
Author: Claudio Fragomeli
Author-email: cla.fragomeli@gmail.com
Requires-Python: >=3.7
License-File: LICENSE
Requires-Dist: SQLAlchemy==1.4.29
Requires-Dist: mysql-connector-python-rf==2.2.2
Requires-Dist: PyYAML==5.4.1
Requires-Dist: pydantic==1.9.0
Requires-Dist: requests==2.25.1
Requires-Dist: pandas==1.3.4
Dynamic: license-file
